{
  "users": [
    {
      "name": "Trung",
      "phone": "0901946596",
      "id": "p9gFyvS-z",
      "email": "tranvantuantrung@gmail.com",
      "password": "4297f44b13955235245b2497399d7a93"
    },
    {
      "name": "Hieu",
      "phone": "0934121213",
      "email": "nguyenhieu@gmail.com",
      "password": "e10adc3949ba59abbe56e057f20f883e",
      "id": "YOYN9SFjK"
    },
    {
      "name": "Thien",
      "phone": "0905050505",
      "email": "nguyencongnhathtien@gmail.com",
      "password": "4297f44b13955235245b2497399d7a93",
      "id": "mT6gE875b"
    }
  ]
}